ocdeployer/__init__.py
ocdeployer/__main__.py
ocdeployer/config.py
ocdeployer/deploy.py
ocdeployer/env.py
ocdeployer/events.py
ocdeployer/images.py
ocdeployer/secrets.py
ocdeployer/templates.py
ocdeployer/utils.py
ocdeployer-5.7.11.dist-info/LICENSE
ocdeployer-5.7.11.dist-info/METADATA
ocdeployer-5.7.11.dist-info/WHEEL
ocdeployer-5.7.11.dist-info/entry_points.txt
ocdeployer-5.7.11.dist-info/top_level.txt
ocdeployer-5.7.11.dist-info/RECORD
