Metadata-Version: 2.1
Name: ocdeployer
Version: 5.7.11
Summary: A tool which wraps the OpenShift command line tools to enable repeatable automated deployment of OpenShift templates
Home-page: https://www.github.com/bsquizz/ocdeployer
Author: Brandon Squizzato
Author-email: bsquizza@redhat.com
License: MIT
Keywords: openshift,kubernetes
Platform: UNKNOWN
Classifier: Topic :: Utilities
Classifier: License :: OSI Approved :: MIT License
Classifier: Programming Language :: Python
Classifier: Programming Language :: Python :: 3
Classifier: Programming Language :: Python :: 3.4
Classifier: Programming Language :: Python :: 3.5
Classifier: Programming Language :: Python :: 3.6
Requires-Python: >=3.5
Requires-Dist: sh (>=1.13.1)
Requires-Dist: prompter
Requires-Dist: pyyaml
Requires-Dist: click
Requires-Dist: appdirs
Requires-Dist: wait-for
Requires-Dist: jinja2
Requires-Dist: cached-property
Requires-Dist: pytz
Requires-Dist: kubernetes
Requires-Dist: anytree
Requires-Dist: ocviapy
